{
  "project_info": {
    "project_number": "766724693754",
    "firebase_url": "https://gatekeep-43867-default-rtdb.asia-southeast1.firebasedatabase.app",
    "project_id": "gatekeep-43867",
    "storage_bucket": "gatekeep-43867.appspot.com"
  },
  "client": [
    {
      "client_info": {
        "mobilesdk_app_id": "1:766724693754:android:f82a3d9135a9dd7ef87343",
        "android_client_info": {
          "package_name": "com.fernandez.gatekeep"
        }
      },
      "oauth_client": [
        {
          "client_id": "766724693754-t81mc6avfecluclovd6c6afohoqr3h61.apps.googleusercontent.com",
          "client_type": 1,
          "android_info": {
            "package_name": "com.fernandez.gatekeep",
            "certificate_hash": "717e3f594b5c5d68ba06190a2d77156c417f3339"
          }
        },
        {
          "client_id": "766724693754-7i7jm2u6tn2hhc5l6k0iq62qu3jk46u6.apps.googleusercontent.com",
          "client_type": 3
        }
      ],
      "api_key": [
        {
          "current_key": "AIzaSyCkQT-EpVz3_ZSIWs9FFBDPLFIjXIphTaM"
        }
      ],
      "services": {
        "appinvite_service": {
          "other_platform_oauth_client": [
            {
              "client_id": "766724693754-7i7jm2u6tn2hhc5l6k0iq62qu3jk46u6.apps.googleusercontent.com",
              "client_type": 3
            }
          ]
        }
      }
    }
  ],
  "configuration_version": "1"
}